radiocut/__init__.py
radiocut_downloader-0.4.dist-info/DESCRIPTION.rst
radiocut_downloader-0.4.dist-info/METADATA
radiocut_downloader-0.4.dist-info/RECORD
radiocut_downloader-0.4.dist-info/WHEEL
radiocut_downloader-0.4.dist-info/entry_points.txt
radiocut_downloader-0.4.dist-info/metadata.json
radiocut_downloader-0.4.dist-info/top_level.txt
