Metadata-Version: 2.0
Name: radiocut-downloader
Version: 0.4
Summary: Download audiocuts from radiocut.fm
Home-page: https://github.com/mgaitan/radiocut_downloader
Author: Martín Gaitán
Author-email: gaitan@gmail.com
License: BSD
Platform: UNKNOWN
Classifier: Development Status :: 4 - Beta
Classifier: Intended Audience :: Developers
Classifier: License :: OSI Approved :: BSD License
Classifier: Natural Language :: English
Classifier: Programming Language :: Python :: 2.7
Classifier: Programming Language :: Python :: 3
Requires-Dist: docopt
Requires-Dist: pyquery
Requires-Dist: requests
Requires-Dist: moviepy
Requires-Dist: python-dateutil
